skill_sdk/__init__.py
skill_sdk/cli.py
skill_sdk/exceptions.py
skill_sdk/http.py
skill_sdk/py.typed
skill_sdk/runtime.py
skill_sdk/schema.py
skill_sdk/skill.py
skill_sdk/types.py
skill_sdk/validation.py
skill_engine_sdk-1.0.0.dist-info/METADATA
skill_engine_sdk-1.0.0.dist-info/WHEEL
skill_engine_sdk-1.0.0.dist-info/entry_points.txt
skill_engine_sdk-1.0.0.dist-info/RECORD
