Metadata-Version: 2.4
Name: skill-engine-sdk
Version: 1.0.0
Summary: Python SDK for building Skill Engine plugins
Project-URL: Homepage, https://www.skill-ai.dev/
Project-URL: Documentation, https://www.skill-ai.dev/api/
Project-URL: Repository, https://github.com/kubiyabot/skill
Project-URL: Issues, https://github.com/kubiyabot/skill/issues
Project-URL: Changelog, https://github.com/kubiyabot/skill/blob/main/sdk/python/CHANGELOG.md
Author: Skill Engine Team
License-Expression: MIT
Keywords: plugins,sdk,skill-engine,wasm
Classifier: Development Status :: 3 - Alpha
Classifier: Intended Audience :: Developers
Classifier: License :: OSI Approved :: MIT License
Classifier: Programming Language :: Python :: 3
Classifier: Programming Language :: Python :: 3.10
Classifier: Programming Language :: Python :: 3.11
Classifier: Programming Language :: Python :: 3.12
Requires-Python: >=3.10
Requires-Dist: pydantic>=2.0
Requires-Dist: pyyaml>=6.0
Requires-Dist: rich>=13.0
Requires-Dist: typer>=0.9
Provides-Extra: build
Requires-Dist: componentize-py>=0.10; extra == 'build'
Provides-Extra: dev
Requires-Dist: black>=23.0; extra == 'dev'
Requires-Dist: mypy>=1.0; extra == 'dev'
Requires-Dist: pytest-asyncio>=0.21; extra == 'dev'
Requires-Dist: pytest>=7.0; extra == 'dev'
Requires-Dist: ruff>=0.1; extra == 'dev'
